user/src/shiftTaps.v
`timescale 1 ns / 1 ns

module shiftTaps #(
        parameter WIDTH = 8,
        parameter SHIFT = 640
    ) (
        input                   clock,
        input                   reset,

        input                   ivalid, 
        input  [WIDTH - 1 : 0]  shiftin,

        output                  ovalid, 
        output [WIDTH - 1 : 0]  shiftout
    );

    reg                     done;
    reg                     valid;
    reg [$clog2(SHIFT)-1:0] count;

    reg [WIDTH-1:0] ram [SHIFT-1:0];
    reg [WIDTH-1:0] odata;

    integer i;
    always @(posedge clock or posedge reset) begin
        if (reset) begin
            count <= 0;
            done <= 0;
            odata <= 0;
            valid <= 0;

            for (i = 0; i < SHIFT; i = i+1) begin
                ram[i] <= 0;
            end
        end 
        else begin            
            if (ivalid) begin
                ram[count] <= shiftin;
                odata <= ram[count];
                count <= count + 1;
                if (count == (SHIFT-1)) begin
                    done <= 1;
                    count <= 0;
                end
                valid <= done;
            end 
            else begin
                valid <= 0;
            end
        end
    end

    assign ovalid = valid;
    assign shiftout = odata;

endmodule

user/src/movingAvg.v
module movingAvg #(
        parameter WIDTH = 32,
        parameter WINDOW = 4
    ) (
        input  clock,
        input  reset,

        input  ivalid,
        input  signed [WIDTH-1:0] idata,

        output ovalid,
        output signed [WIDTH-1:0] odata
    );

    localparam SUM_WIDTH = WIDTH + $clog2(WINDOW);

    reg                    done;
    reg signed [WIDTH-1:0] odata_buf;
    reg signed [(SUM_WIDTH-1):0] sum;

    wire 	                mvalid;
    wire signed [WIDTH-1:0] mdata;
    wire signed [SUM_WIDTH-1:0] ext_old_data = {{$clog2(WINDOW){mdata[WIDTH-1]}}, mdata};
    wire signed [SUM_WIDTH-1:0] ext_new_data = {{$clog2(WINDOW){idata[WIDTH-1]}}, idata};

    shiftTaps #(
        .WIDTH 		( WIDTH   	),
        .SHIFT 		( WINDOW 	))
    u_shiftTaps(
        //ports
        .clock    		( clock    		),
        .reset    		( reset    		),

        .ivalid   		( ivalid   		),
        .shiftin  		( idata  		),

        .ovalid   		( mvalid   		),
        .shiftout 		( mdata 		)
    );

    always @(posedge clock or posedge reset) begin
        if(reset) begin
            odata_buf <= 0;
            sum <= 0;
        end
        else begin
            if (ivalid) begin
                odata_buf <= sum[SUM_WIDTH-1:$clog2(WINDOW)];
                if (done) begin
                    sum <= sum + ext_new_data - ext_old_data;
                end else begin
                    sum <= sum + ext_new_data;
                end
            end
        end
    end

    always @(posedge clock or posedge reset) begin
        if(reset) begin
            done <= 1'b0;
        end
        else begin
            if (mvalid && (~done)) begin
                done <= 1'b1;
            end
            else begin
                done <= done;
            end
        end
    end

    assign odata = odata_buf;
    assign ovalid = mvalid;

endmodule

user/src/utils/ram_2port.v
module ram_2port #(
        parameter DWIDTH=32,
        parameter AWIDTH=9
    ) (
        input clka,
        input ena,
        input wea,
        input [AWIDTH-1:0] addra,
        input [DWIDTH-1:0] dia,
        output reg [DWIDTH-1:0] doa,

        input clkb,
        input enb,
        input web,
        input [AWIDTH-1:0] addrb,
        input [DWIDTH-1:0] dib,
        output reg [DWIDTH-1:0] dob
    );

    reg [DWIDTH-1:0] ram [(1<<AWIDTH)-1:0];
    integer 	     i;
    initial begin
        for(i=0;i<(1<<AWIDTH);i=i+1)
            ram[i] <= {DWIDTH{1'b0}};
        doa <= 0;
        dob <= 0;
    end

    always @(posedge clka) begin
        if (ena) begin
            if (wea) begin
                ram[addra] <= dia;
            end
            doa <= ram[addra];
        end
    end

    always @(posedge clkb) begin
        if (enb) begin
            if (web) begin
                ram[addrb] <= dib;
            end
            dob <= ram[addrb];
        end
    end
    
endmodule // ram_2port

user/src/moving_avg.v
module moving_avg #(
        parameter DATA_WIDTH = 32,
        parameter WINDOW_SHIFT = 4,
        parameter SIGNED = 0
    ) (
        input clock,
        input enable,
        input reset,

        input signed [DATA_WIDTH-1:0] data_in,
        input input_valid,

        output reg signed [DATA_WIDTH-1:0] data_out,
        output reg output_valid
    );

    localparam WINDOW_SIZE = 1<<WINDOW_SHIFT;
    localparam SUM_WIDTH = DATA_WIDTH + WINDOW_SHIFT;

    reg signed [(SUM_WIDTH-1):0] running_sum;

    wire signed [DATA_WIDTH-1:0] old_data;
    wire signed [DATA_WIDTH-1:0] new_data = data_in;

    wire signed [SUM_WIDTH-1:0] ext_old_data = {{WINDOW_SHIFT{old_data[DATA_WIDTH-1]}}, old_data};
    wire signed [SUM_WIDTH-1:0] ext_new_data = {{WINDOW_SHIFT{new_data[DATA_WIDTH-1]}}, new_data};


    reg [WINDOW_SHIFT-1:0] addr;
    reg full;

    ram_2port  #(
        .DWIDTH(DATA_WIDTH), 
        .AWIDTH(WINDOW_SHIFT)) 
    delay_line (
        .clka(clock),
        .ena(1),
        .wea(input_valid),
        .addra(addr),
        .dia(data_in),
        .doa(),
        .clkb(clock),
        .enb(input_valid),
        .web(0),
        .addrb(addr),
        .dib(32'hFFFF),
        .dob(old_data)
    );

    integer i;
    always @(posedge clock) begin
        if (reset) begin
            addr <= 0;
            running_sum <= 0;
            full <= 0;
            data_out <= 0;
        end else if (enable) begin
            if (input_valid) begin
                addr <= addr + 1;
                data_out <= running_sum[SUM_WIDTH-1:WINDOW_SHIFT];

                if (addr == WINDOW_SIZE-1) begin
                    full <= 1;
                end

                if (full) begin
                    running_sum <= running_sum + ext_new_data - ext_old_data;
                end else begin
                    running_sum <= running_sum + ext_new_data;
                end

                output_valid <= full;
            end else begin
                output_valid <= 0;
            end
        end else begin
            output_valid <= 0;
        end
    end
endmodule

user/sim/Apply/Comm/Filter/movingAvg_tb.v
`timescale 1ns / 1ps

module movingAvg_tb;

    // Parameters
    parameter DATA_WIDTH = 32;
    parameter WINDOW_SHIFT = 4;
    parameter WINDOW_SIZE = 1 << WINDOW_SHIFT;
    parameter SIGNED = 0;

    // Inputs
    reg clock;
    reg enable;
    reg reset;
    reg signed [DATA_WIDTH-1:0] data_in;
    reg input_valid;

    // Outputs
    wire signed [DATA_WIDTH-1:0] data_out;
    wire output_valid;

    // Instantiate the DUT (Device Under Test)
    moving_avg #(
        .DATA_WIDTH(DATA_WIDTH),
        .WINDOW_SHIFT(WINDOW_SHIFT),
        .SIGNED(SIGNED)) 
    u_moving_avg (
        .clock(clock),
        .enable(enable),
        .reset(reset),
        .data_in(data_in),
        .input_valid(input_valid),
        .data_out(data_out),
        .output_valid(output_valid)
    );

    wire signed [DATA_WIDTH-1:0] odata;
    wire ovalid;
    movingAvg #(
        .WIDTH(DATA_WIDTH),
        .WINDOW(1<<WINDOW_SHIFT)) 
    u_movingAvg (
        .clock(clock),
        .reset(reset),
        .idata(data_in),
        .ivalid(input_valid),
        .odata(odata),
        .ovalid(ovalid)
    );

    // Clock generation
    initial begin
        clock = 0;
        forever #5 clock = ~clock; // 10 ns clock period
    end

    // Test sequence
    initial begin
        // Initialize inputs
        reset = 1;
        enable = 0;
        data_in = 0;
        input_valid = 0;

        // Apply reset
        #20;
        reset = 0;
        enable = 1;

        // Provide input values and valid signals
        // Test sequence: 16 inputs to fill the window and then some more

        repeat(2) begin
            // Fill the window
            input_data(32'h00000001); // input 1
            input_data(32'h00000002); // input 2
            input_data(32'h00000003); // input 3
            input_data(32'h00000004); // input 4
            input_data(32'h00000005); // input 5
            input_data(32'h00000006); // input 6
            input_data(32'h00000007); // input 7
            input_data(32'h00000008); // input 8
            input_data(32'h00000009); // input 9
            input_data(32'h0000000A); // input 10
            input_data(32'h0000000B); // input 11
            input_data(32'h0000000C); // input 12
            input_data(32'h0000000D); // input 13
            input_data(32'h0000000E); // input 14
            input_data(32'h0000000F); // input 15
            input_data(32'h00000010); // input 16
        end

        // Additional inputs to observe the sliding window behavior
        input_data(32'h00000020); // input 32
        input_data(32'h00000030); // input 48
        input_data(32'h00000040); // input 64
        input_data(32'h00000050); // input 80
        input_data(32'h00000060); // input 96

        // Finish the simulation
        #100;
        $finish;
    end

    // Task to provide input data
    task input_data;
        input [DATA_WIDTH-1:0] data;
        begin
            @(posedge clock);
            data_in = data;
            input_valid = 1;
            @(posedge clock);
            input_valid = 0;
        end
    endtask

    // Monitor the outputs
    initial begin
        $dumpfile("movingAvg.vcd");        
        $dumpvars(0, movingAvg_tb); 
        $monitor("At time %t: data_in = %d, data_out = %d, output_valid = %b",
                 $time, data_in, data_out, output_valid);
    end

endmodule

user/sim/Apply/Comm/Filter/movingAvg.vcd
$date
   Thu Jun 20 15:46:02 2024
$end
$version
  2018.3
$end
$timescale
  1ps
$end
$scope module movingAvg_tb $end
$var reg 1 ! clock $end
$var reg 1 " enable $end
$var reg 1 # reset $end
$var reg 32 $ data_in [31:0] $end
$var reg 1 % input_valid $end
$var wire 32 & data_out [31:0] $end
$var wire 1 ' output_valid $end
$var wire 32 ( odata [31:0] $end
$var wire 1 ) ovalid $end
$var parameter 32 * DATA_WIDTH [31:0] $end
$var parameter 32 + WINDOW_SHIFT [31:0] $end
$var parameter 32 , WINDOW_SIZE [31:0] $end
$var parameter 32 - SIGNED [31:0] $end
$scope module u_moving_avg $end
$var wire 1 . clock $end
$var wire 1 / enable $end
$var wire 1 0 reset $end
$var wire 32 1 data_in [31:0] $end
$var wire 1 2 input_valid $end
$var reg 32 3 data_out [31:0] $end
$var reg 1 4 output_valid $end
$var reg 36 5 running_sum [35:0] $end
$var wire 32 6 old_data [31:0] $end
$var wire 32 7 new_data [31:0] $end
$var wire 36 8 ext_old_data [35:0] $end
$var wire 36 9 ext_new_data [35:0] $end
$var reg 4 : addr [3:0] $end
$var reg 1 ; full $end
$var integer 32 < i $end
$var parameter 32 = DATA_WIDTH [31:0] $end
$var parameter 32 > WINDOW_SHIFT [31:0] $end
$var parameter 32 ? SIGNED [31:0] $end
$var parameter 32 @ WINDOW_SIZE [31:0] $end
$var parameter 32 A SUM_WIDTH [31:0] $end
$scope module delay_line $end
$var wire 1 . clka $end
$var wire 1 B ena $end
$var wire 1 2 wea $end
$var wire 4 C addra [3:0] $end
$var wire 32 1 dia [31:0] $end
$var reg 32 D doa [31:0] $end
$var wire 1 . clkb $end
$var wire 1 2 enb $end
$var wire 1 E web $end
$var wire 4 F addrb [3:0] $end
$var wire 32 G dib [31:0] $end
$var reg 32 H dob [31:0] $end
$var integer 32 I i $end
$var parameter 32 J DWIDTH [31:0] $end
$var parameter 32 K AWIDTH [31:0] $end
$upscope $end
$upscope $end
$scope module u_movingAvg $end
$var wire 1 L clock $end
$var wire 1 M reset $end
$var wire 1 N ivalid $end
$var wire 32 O idata [31:0] $end
$var wire 1 ) ovalid $end
$var wire 32 ( odata [31:0] $end
$var reg 1 P done $end
$var reg 32 Q odata_buf [31:0] $end
$var reg 36 R sum [35:0] $end
$var wire 1 S mvalid $end
$var wire 32 T mdata [31:0] $end
$var wire 36 U ext_old_data [35:0] $end
$var wire 36 V ext_new_data [35:0] $end
$var parameter 32 W WIDTH [31:0] $end
$var parameter 32 X WINDOW [31:0] $end
$var parameter 32 Y SUM_WIDTH [31:0] $end
$scope module u_shiftTaps $end
$var wire 1 L clock $end
$var wire 1 M reset $end
$var wire 1 N ivalid $end
$var wire 32 O shiftin [31:0] $end
$var wire 1 S ovalid $end
$var wire 32 T shiftout [31:0] $end
$var reg 1 Z done $end
$var reg 1 [ valid $end
$var reg 4 \ count [3:0] $end
$var reg 32 ] odata [31:0] $end
$var integer 32 ^ i $end
$var parameter 32 _ WIDTH [31:0] $end
$var parameter 32 ` SHIFT [31:0] $end
$upscope $end
$upscope $end
$scope task input_data $end
$var reg 32 a data [31:0] $end
$upscope $end
$upscope $end
$enddefinitions $end
#0
$dumpvars
0!
0"
1#
b0 $
0%
bx &
x'
b0 (
0)
b100000 *
b100 +
b10000 ,
b0 -
0.
0/
10
b0 1
02
bx 3
x4
bx 5
b0 6
b0 7
b0 8
b0 9
bx :
x;
bx <
b100000 =
b100 >
b0 ?
b10000 @
b100100 A
1B
bx C
b0 D
0E
bx F
b1111111111111111 G
b0 H
b10000 I
b100000 J
b100 K
0L
1M
0N
b0 O
0P
b0 Q
b0 R
0S
b0 T
b0 U
b0 V
b100000 W
b10000 X
b100100 Y
0Z
0[
b0 \
b0 ]
b10000 ^
b100000 _
b10000 `
bx a
$end
#5000
1!
b0 &
1.
b0 3
b0 5
b0 :
0;
b0 C
bx D
b0 F
1L
b10000 ^
#10000
0!
0.
0L
#15000
1!
1.
b0 D
1L
b10000 ^
#20000
0!
1"
0#
0.
1/
00
0L
0M
b1 a
#25000
1!
b1 $
1%
0'
1.
b1 1
12
04
b1 7
b1 9
b1 :
b1 C
b1 F
1L
1N
b1 O
b1 V
b1 \
#30000
0!
0.
0L
#35000
1!
0%
1.
02
1L
0N
b10 a
#40000
0!
0.
0L
#45000
1!
b10 $
1%
1.
b10 1
12
b1 5
b10 7
b10 9
b10 :
b10 C
b10 F
1L
1N
b10 O
b1 R
b10 V
b10 \
#50000
0!
0.
0L
#55000
1!
0%
1.
02
1L
0N
b11 a
#60000
0!
0.
0L
#65000
1!
b11 $
1%
1.
b11 1
12
b11 5
b11 7
b11 9
b11 :
b11 C
b11 F
1L
1N
b11 O
b11 R
b11 V
b11 \
#70000
0!
0.
0L
#75000
1!
0%
1.
02
1L
0N
b100 a
#80000
0!
0.
0L
#85000
1!
b100 $
1%
1.
b100 1
12
b110 5
b100 7
b100 9
b100 :
b100 C
b100 F
1L
1N
b100 O
b110 R
b100 V
b100 \
#90000
0!
0.
0L
#95000
1!
0%
1.
02
1L
0N
b101 a
#100000
0!
0.
0L
#105000
1!
b101 $
1%
1.
b101 1
12
b1010 5
b101 7
b101 9
b101 :
b101 C
b101 F
1L
1N
b101 O
b1010 R
b101 V
b101 \
#110000
0!
0.
0L
#115000
1!
0%
1.
02
1L
0N
b110 a
#120000
0!
0.
0L
#125000
1!
b110 $
1%
1.
b110 1
12
b1111 5
b110 7
b110 9
b110 :
b110 C
b110 F
1L
1N
b110 O
b1111 R
b110 V
b110 \
#130000
0!
0.
0L
#135000
1!
0%
1.
02
1L
0N
b111 a
#140000
0!
0.
0L
#145000
1!
b111 $
1%
1.
b111 1
12
b10101 5
b111 7
b111 9
b111 :
b111 C
b111 F
1L
1N
b111 O
b10101 R
b111 V
b111 \
#150000
0!
0.
0L
#155000
1!
0%
1.
02
1L
0N
b1000 a
#160000
0!
0.
0L
#165000
1!
b1000 $
1%
b1 &
b1 (
1.
b1000 1
12
b1 3
b11100 5
b1000 7
b1000 9
b1000 :
b1000 C
b1000 F
1L
1N
b1000 O
b1 Q
b11100 R
b1000 V
b1000 \
#170000
0!
0.
0L
#175000
1!
0%
1.
02
1L
0N
b1001 a
#180000
0!
0.
0L
#185000
1!
b1001 $
1%
1.
b1001 1
12
b100100 5
b1001 7
b1001 9
b1001 :
b1001 C
b1001 F
1L
1N
b1001 O
b100100 R
b1001 V
b1001 \
#190000
0!
0.
0L
#195000
1!
0%
1.
02
1L
0N
b1010 a
#200000
0!
0.
0L
#205000
1!
b1010 $
1%
b10 &
b10 (
1.
b1010 1
12
b10 3
b101101 5
b1010 7
b1010 9
b1010 :
b1010 C
b1010 F
1L
1N
b1010 O
b10 Q
b101101 R
b1010 V
b1010 \
#210000
0!
0.
0L
#215000
1!
0%
1.
02
1L
0N
b1011 a
#220000
0!
0.
0L
#225000
1!
b1011 $
1%
1.
b1011 1
12
b110111 5
b1011 7
b1011 9
b1011 :
b1011 C
b1011 F
1L
1N
b1011 O
b110111 R
b1011 V
b1011 \
#230000
0!
0.
0L
#235000
1!
0%
1.
02
1L
0N
b1100 a
#240000
0!
0.
0L
#245000
1!
b1100 $
1%
b11 &
b11 (
1.
b1100 1
12
b11 3
b1000010 5
b1100 7
b1100 9
b1100 :
b1100 C
b1100 F
1L
1N
b1100 O
b11 Q
b1000010 R
b1100 V
b1100 \
#250000
0!
0.
0L
#255000
1!
0%
1.
02
1L
0N
b1101 a
#260000
0!
0.
0L
#265000
1!
b1101 $
1%
b100 &
b100 (
1.
b1101 1
12
b100 3
b1001110 5
b1101 7
b1101 9
b1101 :
b1101 C
b1101 F
1L
1N
b1101 O
b100 Q
b1001110 R
b1101 V
b1101 \
#270000
0!
0.
0L
#275000
1!
0%
1.
02
1L
0N
b1110 a
#280000
0!
0.
0L
#285000
1!
b1110 $
1%
1.
b1110 1
12
b1011011 5
b1110 7
b1110 9
b1110 :
b1110 C
b1110 F
1L
1N
b1110 O
b1011011 R
b1110 V
b1110 \
#290000
0!
0.
0L
#295000
1!
0%
1.
02
1L
0N
b1111 a
#300000
0!
0.
0L
#305000
1!
b1111 $
1%
b101 &
b101 (
1.
b1111 1
12
b101 3
b1101001 5
b1111 7
b1111 9
b1111 :
b1111 C
b1111 F
1L
1N
b1111 O
b101 Q
b1101001 R
b1111 V
b1111 \
#310000
0!
0.
0L
#315000
1!
0%
1.
02
1L
0N
b10000 a
#320000
0!
0.
0L
#325000
1!
b10000 $
1%
b110 &
b110 (
1.
b10000 1
12
b110 3
b1111000 5
b10000 7
b10000 9
b0 :
1;
b0 C
b0 F
1L
1N
b10000 O
b110 Q
b1111000 R
b10000 V
1Z
b0 \
#330000
0!
0.
0L
#335000
1!
0%
1.
02
b1 D
1L
0N
b1 a
#340000
0!
0.
0L
#345000
1!
b1 $
1%
b111 &
1'
b111 (
1)
1.
b1 1
12
b111 3
14
b10001000 5
b1 6
b1 7
b1 8
b1 9
b1 :
b1 C
b1 F
b1 H
1L
1N
b1 O
b111 Q
b10001000 R
1S
b1 T
b1 U
b1 V
1[
b1 \
b1 ]
#350000
0!
0.
0L
#355000
1!
0%
0'
0)
1.
02
04
b10 D
1L
0N
1P
0S
0[
b10 a
#360000
0!
0.
0L
#365000
1!
b10 $
1%
b1000 &
1'
b1000 (
1)
1.
b10 1
12
b1000 3
14
b10 6
b10 7
b10 8
b10 9
b10 :
b10 C
b10 F
b10 H
1L
1N
b10 O
b1000 Q
1S
b10 T
b10 U
b10 V
1[
b10 \
b10 ]
#370000
0!
0.
0L
#375000
1!
0%
0'
0)
1.
02
04
b11 D
1L
0N
0S
0[
b11 a
#380000
0!
0.
0L
#385000
1!
b11 $
1%
1'
1)
1.
b11 1
12
14
b11 6
b11 7
b11 8
b11 9
b11 :
b11 C
b11 F
b11 H
1L
1N
b11 O
1S
b11 T
b11 U
b11 V
1[
b11 \
b11 ]
#390000
0!
0.
0L
#395000
1!
0%
0'
0)
1.
02
04
b100 D
1L
0N
0S
0[
b100 a
#400000
0!
0.
0L
#405000
1!
b100 $
1%
1'
1)
1.
b100 1
12
14
b100 6
b100 7
b100 8
b100 9
b100 :
b100 C
b100 F
b100 H
1L
1N
b100 O
1S
b100 T
b100 U
b100 V
1[
b100 \
b100 ]
#410000
0!
0.
0L
#415000
1!
0%
0'
0)
1.
02
04
b101 D
1L
0N
0S
0[
b101 a
#420000
0!
0.
0L
#425000
1!
b101 $
1%
1'
1)
1.
b101 1
12
14
b101 6
b101 7
b101 8
b101 9
b101 :
b101 C
b101 F
b101 H
1L
1N
b101 O
1S
b101 T
b101 U
b101 V
1[
b101 \
b101 ]
#430000
0!
0.
0L
#435000
1!
0%
0'
0)
1.
02
04
b110 D
1L
0N
0S
0[
b110 a
#440000
0!
0.
0L
#445000
1!
b110 $
1%
1'
1)
1.
b110 1
12
14
b110 6
b110 7
b110 8
b110 9
b110 :
b110 C
b110 F
b110 H
1L
1N
b110 O
1S
b110 T
b110 U
b110 V
1[
b110 \
b110 ]
#450000
0!
0.
0L
#455000
1!
0%
0'
0)
1.
02
04
b111 D
1L
0N
0S
0[
b111 a
#460000
0!
0.
0L
#465000
1!
b111 $
1%
1'
1)
1.
b111 1
12
14
b111 6
b111 7
b111 8
b111 9
b111 :
b111 C
b111 F
b111 H
1L
1N
b111 O
1S
b111 T
b111 U
b111 V
1[
b111 \
b111 ]
#470000
0!
0.
0L
#475000
1!
0%
0'
0)
1.
02
04
b1000 D
1L
0N
0S
0[
b1000 a
#480000
0!
0.
0L
#485000
1!
b1000 $
1%
1'
1)
1.
b1000 1
12
14
b1000 6
b1000 7
b1000 8
b1000 9
b1000 :
b1000 C
b1000 F
b1000 H
1L
1N
b1000 O
1S
b1000 T
b1000 U
b1000 V
1[
b1000 \
b1000 ]
#490000
0!
0.
0L
#495000
1!
0%
0'
0)
1.
02
04
b1001 D
1L
0N
0S
0[
b1001 a
#500000
0!
0.
0L
#505000
1!
b1001 $
1%
1'
1)
1.
b1001 1
12
14
b1001 6
b1001 7
b1001 8
b1001 9
b1001 :
b1001 C
b1001 F
b1001 H
1L
1N
b1001 O
1S
b1001 T
b1001 U
b1001 V
1[
b1001 \
b1001 ]
#510000
0!
0.
0L
#515000
1!
0%
0'
0)
1.
02
04
b1010 D
1L
0N
0S
0[
b1010 a
#520000
0!
0.
0L
#525000
1!
b1010 $
1%
1'
1)
1.
b1010 1
12
14
b1010 6
b1010 7
b1010 8
b1010 9
b1010 :
b1010 C
b1010 F
b1010 H
1L
1N
b1010 O
1S
b1010 T
b1010 U
b1010 V
1[
b1010 \
b1010 ]
#530000
0!
0.
0L
#535000
1!
0%
0'
0)
1.
02
04
b1011 D
1L
0N
0S
0[
b1011 a
#540000
0!
0.
0L
#545000
1!
b1011 $
1%
1'
1)
1.
b1011 1
12
14
b1011 6
b1011 7
b1011 8
b1011 9
b1011 :
b1011 C
b1011 F
b1011 H
1L
1N
b1011 O
1S
b1011 T
b1011 U
b1011 V
1[
b1011 \
b1011 ]
#550000
0!
0.
0L
#555000
1!
0%
0'
0)
1.
02
04
b1100 D
1L
0N
0S
0[
b1100 a
#560000
0!
0.
0L
#565000
1!
b1100 $
1%
1'
1)
1.
b1100 1
12
14
b1100 6
b1100 7
b1100 8
b1100 9
b1100 :
b1100 C
b1100 F
b1100 H
1L
1N
b1100 O
1S
b1100 T
b1100 U
b1100 V
1[
b1100 \
b1100 ]
#570000
0!
0.
0L
#575000
1!
0%
0'
0)
1.
02
04
b1101 D
1L
0N
0S
0[
b1101 a
#580000
0!
0.
0L
#585000
1!
b1101 $
1%
1'
1)
1.
b1101 1
12
14
b1101 6
b1101 7
b1101 8
b1101 9
b1101 :
b1101 C
b1101 F
b1101 H
1L
1N
b1101 O
1S
b1101 T
b1101 U
b1101 V
1[
b1101 \
b1101 ]
#590000
0!
0.
0L
#595000
1!
0%
0'
0)
1.
02
04
b1110 D
1L
0N
0S
0[
b1110 a
#600000
0!
0.
0L
#605000
1!
b1110 $
1%
1'
1)
1.
b1110 1
12
14
b1110 6
b1110 7
b1110 8
b1110 9
b1110 :
b1110 C
b1110 F
b1110 H
1L
1N
b1110 O
1S
b1110 T
b1110 U
b1110 V
1[
b1110 \
b1110 ]
#610000
0!
0.
0L
#615000
1!
0%
0'
0)
1.
02
04
b1111 D
1L
0N
0S
0[
b1111 a
#620000
0!
0.
0L
#625000
1!
b1111 $
1%
1'
1)
1.
b1111 1
12
14
b1111 6
b1111 7
b1111 8
b1111 9
b1111 :
b1111 C
b1111 F
b1111 H
1L
1N
b1111 O
1S
b1111 T
b1111 U
b1111 V
1[
b1111 \
b1111 ]
#630000
0!
0.
0L
#635000
1!
0%
0'
0)
1.
02
04
b10000 D
1L
0N
0S
0[
b10000 a
#640000
0!
0.
0L
#645000
1!
b10000 $
1%
1'
1)
1.
b10000 1
12
14
b10000 6
b10000 7
b10000 8
b10000 9
b0 :
b0 C
b0 F
b10000 H
1L
1N
b10000 O
1S
b10000 T
b10000 U
b10000 V
1[
b0 \
b10000 ]
#650000
0!
0.
0L
#655000
1!
0%
0'
0)
1.
02
04
b1 D
1L
0N
0S
0[
b100000 a
#660000
0!
0.
0L
#665000
1!
b100000 $
1%
1'
1)
1.
b100000 1
12
14
b1 6
b100000 7
b1 8
b100000 9
b1 :
b1 C
b1 F
b1 H
1L
1N
b100000 O
1S
b1 T
b1 U
b100000 V
1[
b1 \
b1 ]
#670000
0!
0.
0L
#675000
1!
0%
0'
0)
1.
02
04
b10 D
1L
0N
0S
0[
b110000 a
#680000
0!
0.
0L
#685000
1!
b110000 $
1%
1'
1)
1.
b110000 1
12
14
b10100111 5
b10 6
b110000 7
b10 8
b110000 9
b10 :
b10 C
b10 F
b10 H
1L
1N
b110000 O
b10100111 R
1S
b10 T
b10 U
b110000 V
1[
b10 \
b10 ]
#690000
0!
0.
0L
#695000
1!
0%
0'
0)
1.
02
04
b11 D
1L
0N
0S
0[
b1000000 a
#700000
0!
0.
0L
#705000
1!
b1000000 $
1%
b1010 &
1'
b1010 (
1)
1.
b1000000 1
12
b1010 3
14
b11010101 5
b11 6
b1000000 7
b11 8
b1000000 9
b11 :
b11 C
b11 F
b11 H
1L
1N
b1000000 O
b1010 Q
b11010101 R
1S
b11 T
b11 U
b1000000 V
1[
b11 \
b11 ]
#710000
0!
0.
0L
#715000
1!
0%
0'
0)
1.
02
04
b100 D
1L
0N
0S
0[
b1010000 a
#720000
0!
0.
0L
#725000
1!
b1010000 $
1%
b1101 &
1'
b1101 (
1)
1.
b1010000 1
12
b1101 3
14
b100010010 5
b100 6
b1010000 7
b100 8
b1010000 9
b100 :
b100 C
b100 F
b100 H
1L
1N
b1010000 O
b1101 Q
b100010010 R
1S
b100 T
b100 U
b1010000 V
1[
b100 \
b100 ]
#730000
0!
0.
0L
#735000
1!
0%
0'
0)
1.
02
04
b101 D
1L
0N
0S
0[
b1100000 a
#740000
0!
0.
0L
#745000
1!
b1100000 $
1%
b10001 &
1'
b10001 (
1)
1.
b1100000 1
12
b10001 3
14
b101011110 5
b101 6
b1100000 7
b101 8
b1100000 9
b101 :
b101 C
b101 F
b101 H
1L
1N
b1100000 O
b10001 Q
b101011110 R
1S
b101 T
b101 U
b1100000 V
1[
b101 \
b101 ]
#750000
0!
0.
0L
#755000
1!
0%
0'
0)
1.
02
04
b110 D
1L
0N
0S
0[
