user/sim/basic.v
module basic_tb();

    parameter DATA_WIDTH = 32;
    parameter ADDR_WIDTH = 32;
    parameter MAIN_FRE   = 100; //unit MHz
    reg                   sys_clk = 1;
    reg                   sys_rst = 1;
    reg [DATA_WIDTH-1:0]  data;

    always begin
        #(500/MAIN_FRE) sys_clk <= ~sys_clk;
    end

    always begin
        #45 sys_rst <= 0;
    end

    // rst as valid 
    // always @(posedge sys_clk or posedge sys_rst) begin
    //     if (sys_rst) begin
    //         data <= 0;
    //     end
    //     else begin
    //         data <= data + 1;
    //     end
    // end

    // valid after rst
    // reg ivalid;
    // always @(posedge sys_clk or posedge sys_rst) begin
    //     if (sys_rst) begin
    //         ivalid <= 0;
    //     end
    //     else begin
    //         ivalid <= 1;
    //     end
    // end

    always @(posedge sys_clk or posedge sys_rst) begin
        if (sys_rst) begin
            data <= 0;
        end
        else begin
            if (~sys_rst) begin
                data <= data + 1;
            end
        end
    end

    reg                   ovalid;
    reg [DATA_WIDTH-1:0]  odata;
    always @(posedge sys_clk or posedge sys_rst) begin
        if (sys_rst) begin
            ovalid <= 0;
            odata <= 0;
        end 
        else begin            
            if (~sys_rst) begin
                ovalid <= ~sys_rst;
                odata <= data;
            end
        end
    end

    // display & strobe
    always @(posedge sys_clk) begin
        if (~sys_rst) begin
            $display("$display :\tivalid:%d\tdata:%d", ~sys_rst, $signed(data));
            $strobe("$strobe :\tivalid:%d\tdata:%d", ~sys_rst, $signed(data));
        end
    end

    initial begin
        $dumpfile("/home/icer/Project/library/user/sim/basic.vcd");        
        $dumpvars(0, basic_tb);    
        #500 $finish;
    end


endmodule  //TOP

user/sim/basic.vcd
$date
	Thu Jul  4 16:01:04 2024
$end

$version
	Synopsys VCS version L-2016.06_Full64
$end

$timescale
	1s
$end

$comment Csum: 1 5d45c1da457cdb3d $end


$scope module basic_tb $end
$var reg 1 ! sys_clk $end
$var reg 1 " sys_rst $end
$var reg 32 # data [31:0] $end
$var reg 1 $ ovalid $end
$var reg 32 % odata [31:0] $end
$upscope $end

$enddefinitions $end

#0
$dumpvars
0$
1!
1"
b00000000000000000000000000000000 #
b00000000000000000000000000000000 %
$end
#5
0!
#10
1!
#15
0!
#20
1!
#25
0!
#30
1!
#35
0!
#40
1!
#45
0"
0!
#50
1!
b00000000000000000000000000000001 #
1$
#55
0!
#60
1!
b00000000000000000000000000000010 #
b00000000000000000000000000000001 %
#65
0!
#70
1!
b00000000000000000000000000000011 #
b00000000000000000000000000000010 %
#75
0!
#80
1!
b00000000000000000000000000000100 #
b00000000000000000000000000000011 %
#85
0!
#90
1!
b00000000000000000000000000000101 #
b00000000000000000000000000000100 %
#95
0!
#100
1!
b00000000000000000000000000000110 #
b00000000000000000000000000000101 %
#105
0!
#110
1!
b00000000000000000000000000000111 #
b00000000000000000000000000000110 %
#115
0!
#120
1!
b00000000000000000000000000001000 #
b00000000000000000000000000000111 %
#125
0!
#130
1!
b00000000000000000000000000001001 #
b00000000000000000000000000001000 %
#135
0!
#140
1!
b00000000000000000000000000001010 #
b00000000000000000000000000001001 %
#145
0!
#150
1!
b00000000000000000000000000001011 #
b00000000000000000000000000001010 %
#155
0!
#160
1!
b00000000000000000000000000001100 #
b00000000000000000000000000001011 %
#165
0!
#170
1!
b00000000000000000000000000001101 #
b00000000000000000000000000001100 %
#175
0!
#180
1!
b00000000000000000000000000001110 #
b00000000000000000000000000001101 %
#185
0!
#190
1!
b00000000000000000000000000001111 #
b00000000000000000000000000001110 %
#195
0!
#200
1!
b00000000000000000000000000010000 #
b00000000000000000000000000001111 %
#205
0!
#210
1!
b00000000000000000000000000010001 #
b00000000000000000000000000010000 %
#215
0!
#220
1!
b00000000000000000000000000010010 #
b00000000000000000000000000010001 %
#225
0!
#230
1!
b00000000000000000000000000010011 #
b00000000000000000000000000010010 %
#235
0!
#240
1!
b00000000000000000000000000010100 #
b00000000000000000000000000010011 %
#245
0!
#250
1!
b00000000000000000000000000010101 #
b00000000000000000000000000010100 %
#255
0!
#260
1!
b00000000000000000000000000010110 #
b00000000000000000000000000010101 %
#265
0!
#270
1!
b00000000000000000000000000010111 #
b00000000000000000000000000010110 %
#275
0!
#280
1!
b00000000000000000000000000011000 #
b00000000000000000000000000010111 %
#285
0!
#290
1!
b00000000000000000000000000011001 #
b00000000000000000000000000011000 %
#295
0!
#300
1!
b00000000000000000000000000011010 #
b00000000000000000000000000011001 %
#305
0!
#310
1!
b00000000000000000000000000011011 #
b00000000000000000000000000011010 %
#315
0!
#320
1!
b00000000000000000000000000011100 #
b00000000000000000000000000011011 %
#325
0!
#330
1!
b00000000000000000000000000011101 #
b00000000000000000000000000011100 %
#335
0!
#340
1!
b00000000000000000000000000011110 #
b00000000000000000000000000011101 %
#345
0!
#350
1!
b00000000000000000000000000011111 #
b00000000000000000000000000011110 %
#355
0!
#360
1!
b00000000000000000000000000100000 #
b00000000000000000000000000011111 %
#365
0!
#370
1!
b00000000000000000000000000100001 #
b00000000000000000000000000100000 %
#375
0!
#380
1!
b00000000000000000000000000100010 #
b00000000000000000000000000100001 %
#385
0!
#390
1!
b00000000000000000000000000100011 #
b00000000000000000000000000100010 %
#395
0!
#400
1!
b00000000000000000000000000100100 #
b00000000000000000000000000100011 %
#405
0!
#410
1!
b00000000000000000000000000100101 #
b00000000000000000000000000100100 %
#415
0!
#420
1!
b00000000000000000000000000100110 #
b00000000000000000000000000100101 %
#425
0!
#430
1!
b00000000000000000000000000100111 #
b00000000000000000000000000100110 %
#435
0!
#440
1!
b00000000000000000000000000101000 #
b00000000000000000000000000100111 %
#445
0!
#450
1!
b00000000000000000000000000101001 #
b00000000000000000000000000101000 %
#455
0!
#460
1!
b00000000000000000000000000101010 #
b00000000000000000000000000101001 %
#465
0!
#470
1!
b00000000000000000000000000101011 #
b00000000000000000000000000101010 %
#475
0!
#480
1!
b00000000000000000000000000101100 #
b00000000000000000000000000101011 %
#485
0!
#490
1!
b00000000000000000000000000101101 #
b00000000000000000000000000101100 %
