user/src/modulus.v
module modulus #(
        parameter WIDTH = 16
    ) (
        input clock,
        input reset,

        input ivalid,
        input signed [WIDTH-1:0] i,
        input signed [WIDTH-1:0] q,

        output                   ovalid,
        output reg [WIDTH-1:0]   modulus
    );

    reg [WIDTH-1:0] abs_i;
    reg [WIDTH-1:0] abs_q;

    reg [WIDTH-1:0] max;
    reg[ WIDTH-1:0] min;

    // delay #(
    //     .WIDTH(1), 
    //     .DELAY(3)) 
    // stb_delay_inst (
    //     .clock(clock),
    //     .reset(reset),

    //     .idata(ivalid),
    //     .odata(ovalid)
    // );

    reg [2:0] ovalid_buf;

    always @(posedge clock or posedge reset) begin
        if (reset) begin
            ovalid_buf <= 0;
        end 
        else begin    
            ovalid_buf <= {ovalid_buf[1:0], ivalid};
        end
    end
    assign ovalid = ovalid_buf[2];

    // http://dspguru.com/dsp/tricks/magnitude-estimator
    // alpha = 1, beta = 1/4
    // avg err 0.006
    always @(posedge clock or posedge reset) begin
        if (reset) begin
            modulus <= 0;
            abs_i <= 0;
            abs_q <= 0;
            max <= 0;
            min <= 0;
        end 
        else if (ivalid) begin
            abs_i <= i[WIDTH-1] ? (~i+1) : i;
            abs_q <= q[WIDTH-1] ? (~q+1) : q;

        end
        max <= (abs_i > abs_q) ? abs_i : abs_q;
        min <= (abs_i > abs_q) ? abs_q : abs_i;

        modulus <= max + (min>>2);
    end

endmodule

user/sim/Basic/Math/modulus_tb.v
`timescale 1ns / 1ps

module modulus_tb();

    // Parameters
    parameter DATA_WIDTH = 16;

    // Inputs
    reg clock;
    reg enable;
    reg reset;
    reg signed [DATA_WIDTH-1:0] i;
    reg signed [DATA_WIDTH-1:0] q;
    reg input_valid;

    // Outputs
    wire [DATA_WIDTH-1:0] mag;
    wire mag_stb;

    // Instantiate the DUT (Device Under Test)
    modulus #(
        .WIDTH(DATA_WIDTH)) 
    dut (
        .clock(clock),
        .reset(reset),
        .i(i),
        .q(q),
        .ivalid(input_valid),
        .modulus(mag),
        .ovalid(mag_stb)
    );

    // Clock generation
    initial begin
        clock = 0;
        forever #5 clock = ~clock; // 10 ns clock period
    end

    initial begin
        $dumpfile("modulus.vcd");        
        $dumpvars(0, modulus_tb);   
    end
    
    // Test sequence
    initial begin
        // Initialize inputs
        enable = 0;
        reset = 1;
        i = 0;
        q = 0;
        input_valid = 0;

        // Apply reset
        #10;
        reset = 0;
        enable = 1;

        // Test case 1: i = 4, q = 3
        #10;
        i = 4;
        q = 3;
        input_valid = 1;
        #10;
        input_valid = 0;

        // Wait for output
        #30;
        $display("Test case 1: i=4, q=3 | mag=%d, mag_stb=%b (Expected mag=5)", mag, mag_stb);

        // Test case 2: i = -8, q = 7
        #10;
        i = -8;
        q = 7;
        input_valid = 1;
        #10;
        input_valid = 0;

        // Wait for output
        #30;
        $display("Test case 2: i=-8, q=7 | mag=%d, mag_stb=%b (Expected mag=11)", mag, mag_stb);

        // Test case 3: i = 2, q = -3
        #10;
        i = 2;
        q = -3;
        input_valid = 1;
        #10;
        input_valid = 0;

        // Wait for output
        #30;
        $display("Test case 3: i=2, q=-3 | mag=%d, mag_stb=%b (Expected mag=3)", mag, mag_stb);

        // End simulation
        #30;
        $finish;
    end

endmodule

user/sim/Basic/Math/modulus.vcd
$date
   Thu Jun 20 10:40:41 2024
$end
$version
  2018.3
$end
$timescale
  1ps
$end
$scope module modulus_tb $end
$var reg 1 ! clock $end
$var reg 1 " enable $end
$var reg 1 # reset $end
$var reg 16 $ i [15:0] $end
$var reg 16 % q [15:0] $end
$var reg 1 & input_valid $end
$var wire 16 ' mag [15:0] $end
$var wire 1 ( mag_stb $end
$var parameter 32 ) DATA_WIDTH [31:0] $end
$scope module dut $end
$var wire 1 * clock $end
$var wire 1 + reset $end
$var wire 1 , ivalid $end
$var wire 16 - i [15:0] $end
$var wire 16 . q [15:0] $end
$var wire 1 ( ovalid $end
$var reg 16 / modulus [15:0] $end
$var reg 16 0 abs_i [15:0] $end
$var reg 16 1 abs_q [15:0] $end
$var reg 16 2 max [15:0] $end
$var reg 16 3 min [15:0] $end
$var reg 3 4 ovalid_buf [2:0] $end
$var parameter 32 5 WIDTH [31:0] $end
$upscope $end
$upscope $end
$enddefinitions $end
#0
$dumpvars
0!
0"
1#
b0 $
b0 %
0&
bx '
0(
b10000 )
0*
1+
0,
b0 -
b0 .
bx /
b0 0
b0 1
bx 2
bx 3
b0 4
b10000 5
$end
#5000
1!
1*
bx /
b0 2
b0 3
#10000
0!
1"
0#
0*
0+
#15000
1!
b0 '
1*
b0 /
#20000
0!
b100 $
b11 %
1&
0*
1,
b100 -
b11 .
#25000
1!
1*
b100 0
b11 1
b1 4
#30000
0!
0&
0*
0,
#35000
1!
1*
b100 2
b11 3
b10 4
#40000
0!
0*
#45000
1!
b100 '
1(
1*
b100 /
b100 4
#50000
0!
0*
#55000
1!
0(
1*
b0 4
#60000
0!
0*
#65000
1!
1*
#70000
0!
b1111111111111000 $
b111 %
1&
0*
1,
b1111111111111000 -
b111 .
#75000
1!
1*
b1000 0
b111 1
b1 4
#80000
0!
0&
0*
0,
#85000
1!
1*
b1000 2
b111 3
b10 4
#90000
0!
0*
#95000
1!
b1001 '
1(
1*
b1001 /
b100 4
#100000
0!
0*
#105000
1!
0(
1*
b0 4
#110000
0!
0*
#115000
1!
1*
#120000
0!
b10 $
b1111111111111101 %
1&
0*
1,
b10 -
b1111111111111101 .
#125000
1!
1*
b10 0
b11 1
b1 4
#130000
0!
0&
0*
0,
#135000
1!
1*
b11 2
b10 3
b10 4
#140000
0!
0*
#145000
1!
b11 '
1(
1*
b11 /
b100 4
#150000
0!
0*
#155000
1!
0(
1*
b0 4
